mdvorak
