Metadata-Version: 1.1
Name: mdvorak.recipe.qooxdoo
Version: 1.0
Summary: Buildout recipe for Qooxdoo projects.
Home-page: https://bitbucket.org/mdvorak/qooxdoo-recipe/wiki/Home
Author: Michal Dvorak
Author-email: mikee@mdvorak.org
License: Simplified BSD License
Keywords: buildout recipe qooxdoo
Platform: UNKNOWN
Classifier: Development Status :: 5 - Production/Stable
Classifier: Intended Audience :: Developers
Classifier: License :: OSI Approved :: BSD License
Classifier: Operating System :: OS Independent
Classifier: Programming Language :: Python
Classifier: Programming Language :: Python :: 2.7
